[
  {
    "id": "4OFX3Dy0inpClzZcq8lJl0",
    "name": "Charles Pasi",
    "genres": [],
    "followers": 33460,
    "monthlyListeners": 0,
    "image": "https://i.scdn.co/image/ab6761610000e5eb4e810a38c93b6b43c6e14f9c",
    "preview_url": "",
    "source": "spotify",
    "savedAt": "2025-06-04T17:30:32.694Z"
  },
  {
    "id": "2WKdxPFRD7IqZvlIAvhMgY",
    "name": "Fugees",
    "genres": [
      "east coast hip hop"
    ],
    "followers": 1590414,
    "monthlyListeners": 0,
    "image": "https://i.scdn.co/image/dd757e1fca99ac0a3da9aa6c2969bc696cc672ce",
    "preview_url": "",
    "source": "spotify",
    "savedAt": "2025-06-04T17:30:32.694Z"
  },
  {
    "id": "4cEwEednPwWCdYT7ZhROZe",
    "name": "Marc Broussard",
    "genres": [
      "blues"
    ],
    "followers": 190424,
    "monthlyListeners": 0,
    "image": "https://i.scdn.co/image/ab6761610000e5ebc78a80d480018ec030aade25",
    "preview_url": "",
    "source": "spotify",
    "savedAt": "2025-06-04T17:30:32.694Z"
  },
  {
    "id": "0gP5wSp6he2gUcPa5gunV8",
    "name": "MELL VF",
    "genres": [],
    "followers": 32464,
    "monthlyListeners": 0,
    "image": "https://i.scdn.co/image/ab6761610000e5ebb6ab52fead44b9b868f45fca",
    "preview_url": "",
    "source": "spotify",
    "savedAt": "2025-06-04T17:30:32.694Z"
  },
  {
    "id": "72Pauuctba5lMzC89R0Vk0",
    "name": "Vintage Trouble",
    "genres": [
      "blues rock",
      "retro soul",
      "modern blues",
      "retro pop",
      "blues"
    ],
    "followers": 128365,
    "monthlyListeners": 0,
    "image": "https://i.scdn.co/image/ab6761610000e5eba9aaa1e407e86a9e2109b81e",
    "preview_url": "",
    "source": "spotify",
    "savedAt": "2025-06-04T17:30:32.694Z"
  },
  {
    "id": "2FjkZT851ez950cyPjeYid",
    "name": "Bobby McFerrin",
    "genres": [],
    "followers": 264024,
    "monthlyListeners": 0,
    "image": "https://i.scdn.co/image/733bc7148161594837facf51d8b3608f116d0776",
    "preview_url": "",
    "source": "spotify",
    "savedAt": "2025-06-04T17:30:32.694Z"
  },
  {
    "id": "492hDmhPyuIjP3MgTcIqgm",
    "name": "Caro Emerald",
    "genres": [
      "electro swing",
      "swing music",
      "jazz blues"
    ],
    "followers": 393096,
    "monthlyListeners": 0,
    "image": "https://i.scdn.co/image/ab6761610000e5eb379e885a01898367bfcd0c44",
    "preview_url": "",
    "source": "spotify",
    "savedAt": "2025-06-04T17:30:32.694Z"
  },
  {
    "id": "1blgL26JbtaUUKUEMR6Hs2",
    "name": "Gemma Hayes",
    "genres": [],
    "followers": 28133,
    "monthlyListeners": 0,
    "image": "https://i.scdn.co/image/ab6761610000e5eb8b8379950d3d09c5caa2b4fa",
    "preview_url": "",
    "source": "spotify",
    "savedAt": "2025-06-04T17:30:32.694Z"
  },
  {
    "id": "4HfoncnCuBS7D4xU4VDosQ",
    "name": "Southern Avenue",
    "genres": [
      "modern blues",
      "blues",
      "soul blues",
      "blues rock"
    ],
    "followers": 33836,
    "monthlyListeners": 0,
    "image": "https://i.scdn.co/image/ab6761610000e5eb20606d61040ff1b1116615b3",
    "preview_url": "",
    "source": "spotify",
    "savedAt": "2025-06-04T17:30:32.694Z"
  },
  {
    "id": "29WzbAQtDnBJF09es0uddn",
    "name": "Corinne Bailey Rae",
    "genres": [],
    "followers": 841773,
    "monthlyListeners": 0,
    "image": "https://i.scdn.co/image/ab6761610000e5ebdcb57d08016c41fca3e221ab",
    "preview_url": "",
    "source": "spotify",
    "savedAt": "2025-06-04T17:30:32.694Z"
  },
  {
    "id": "4gzpq5DPGxSnKTe4SA8HAU",
    "name": "Coldplay",
    "genres": [],
    "followers": 58616969,
    "monthlyListeners": 0,
    "image": "https://i.scdn.co/image/ab6761610000e5eb1ba8fc5f5c73e7e9313cc6eb",
    "preview_url": "",
    "source": "spotify",
    "savedAt": "2025-06-04T17:30:32.694Z"
  },
  {
    "id": "7oPgCQqMMXEXrNau5vxYZP",
    "name": "Tracy Chapman",
    "genres": [],
    "followers": 1978533,
    "monthlyListeners": 0,
    "image": "https://i.scdn.co/image/965060777aeacb43659097cddc16b741785a508f",
    "preview_url": "",
    "source": "spotify",
    "savedAt": "2025-06-04T17:30:32.694Z"
  },
  {
    "id": "5qzKP2802dITzjsTbj2zWr",
    "name": "Garrett LeBeau",
    "genres": [
      "blues"
    ],
    "followers": 505,
    "monthlyListeners": 0,
    "image": "https://i.scdn.co/image/ab6761610000e5ebb51612e27cb3b68fb7dcf123",
    "preview_url": "",
    "source": "spotify",
    "savedAt": "2025-06-04T17:30:32.694Z"
  },
  {
    "id": "0xeI9Z0Uhs8bYGBRpqq88X",
    "name": "Otis Spann",
    "genres": [
      "blues",
      "classic blues",
      "boogie-woogie",
      "jazz blues"
    ],
    "followers": 58526,
    "monthlyListeners": 0,
    "image": "https://i.scdn.co/image/663f36db2a3d7d18d47573eff16ee4b9dc4cfc5f",
    "preview_url": "",
    "source": "spotify",
    "savedAt": "2025-06-04T17:30:32.694Z"
  },
  {
    "id": "5n1XQGBfQhNsALjJs0APL5",
    "name": "Beth Hart, Joe Bonamassa",
    "genres": [
      "blues",
      "blues rock",
      "modern blues",
      "soul blues"
    ],
    "followers": 41919,
    "monthlyListeners": 0,
    "image": "https://i.scdn.co/image/ab67616d0000b2730c320ab42bd98283d52ec196",
    "preview_url": "",
    "source": "spotify",
    "savedAt": "2025-06-04T17:30:32.694Z"
  },
  {
    "id": "7j46Sze6UWb7p41IqcYFAp",
    "name": "Catherine Russell",
    "genres": [
      "vocal jazz",
      "swing music",
      "jazz"
    ],
    "followers": 35617,
    "monthlyListeners": 0,
    "image": "https://i.scdn.co/image/ab6761610000e5eb3ccf6d9ffc084b4e593bed07",
    "preview_url": "",
    "source": "spotify",
    "savedAt": "2025-06-04T17:30:32.694Z"
  },
  {
    "id": "4l2MwXYwUDQKHcUXwCZjEz",
    "name": "José James",
    "genres": [
      "vocal jazz"
    ],
    "followers": 158700,
    "monthlyListeners": 0,
    "image": "https://i.scdn.co/image/ab6761610000e5eb862d327c65cf3a0e4307e1a3",
    "preview_url": "",
    "source": "spotify",
    "savedAt": "2025-06-04T17:30:32.694Z"
  },
  {
    "id": "34mu675oQQ5ZNuK1soZrIn",
    "name": "Danielle Nicole",
    "genres": [
      "blues",
      "modern blues",
      "blues rock",
      "soul blues"
    ],
    "followers": 36783,
    "monthlyListeners": 0,
    "image": "https://i.scdn.co/image/ab6761610000e5eb34e9fc734631c8e87c78ef55",
    "preview_url": "",
    "source": "spotify",
    "savedAt": "2025-06-04T17:30:32.694Z"
  },
  {
    "id": "13saZpZnCDWOI9D4IJhp1f",
    "name": "Lily Allen",
    "genres": [],
    "followers": 2156973,
    "monthlyListeners": 0,
    "image": "https://i.scdn.co/image/ab6761610000e5eb4816f55146bf03d294005165",
    "preview_url": "",
    "source": "spotify",
    "savedAt": "2025-06-04T17:30:32.694Z"
  },
  {
    "id": "0FLx5Ts7ydf1NuSsy334eU",
    "name": "Stan Taylor",
    "genres": [],
    "followers": 28254,
    "monthlyListeners": 0,
    "image": "https://i.scdn.co/image/ab6761610000e5ebd77c8cfcad811424feb6487b",
    "preview_url": "",
    "source": "spotify",
    "savedAt": "2025-06-04T17:30:32.694Z"
  },
  {
    "id": "4C50EbCS11M0VbGyH3OfLt",
    "name": "Bahamas",
    "genres": [],
    "followers": 400447,
    "monthlyListeners": 0,
    "image": "https://i.scdn.co/image/ab6761610000e5eb9b253d0247e6d9336bc16386",
    "preview_url": "",
    "source": "spotify",
    "savedAt": "2025-06-04T17:30:32.694Z"
  },
  {
    "id": "5rxxzsO9zojzg0FfWVmIv7",
    "name": "shiv",
    "genres": [
      "uk r&b"
    ],
    "followers": 17384,
    "monthlyListeners": 0,
    "image": "https://i.scdn.co/image/ab6761610000e5eb01ec14f2c57dfbe8ce1b0a94",
    "preview_url": "",
    "source": "spotify",
    "savedAt": "2025-06-04T17:30:32.694Z"
  },
  {
    "id": "3qnGvpP8Yth1AqSBMqON5x",
    "name": "Leon Bridges",
    "genres": [
      "retro soul"
    ],
    "followers": 1850367,
    "monthlyListeners": 0,
    "image": "https://i.scdn.co/image/ab6761610000e5ebd5112a5b16a01e971ebb049c",
    "preview_url": "",
    "source": "spotify",
    "savedAt": "2025-06-04T17:30:32.694Z"
  },
  {
    "id": "43NpjLskaVb5j2Jgt6fdbP",
    "name": "Pieta Brown",
    "genres": [
      "americana",
      "alt country"
    ],
    "followers": 14137,
    "monthlyListeners": 0,
    "image": "https://i.scdn.co/image/ab6761610000e5ebff64d9c7470bedfb0e9ed1e3",
    "preview_url": "",
    "source": "spotify",
    "savedAt": "2025-06-04T17:30:32.694Z"
  },
  {
    "id": "1c4rxrxy8eDLvMVL1DTiBe",
    "name": "Andra Day",
    "genres": [
      "soft pop"
    ],
    "followers": 455364,
    "monthlyListeners": 0,
    "image": "https://i.scdn.co/image/ab6761610000e5ebfc6652ad89be0ca09f5caad6",
    "preview_url": "",
    "source": "spotify",
    "savedAt": "2025-06-04T17:30:32.694Z"
  },
  {
    "id": "00x1fYSGhdqScXBRpSj3DW",
    "name": "Olivia Dean",
    "genres": [
      "pop soul"
    ],
    "followers": 668359,
    "monthlyListeners": 0,
    "image": "https://i.scdn.co/image/ab6761610000e5eb5db3dd0534055e889f9e9503",
    "preview_url": "",
    "source": "spotify",
    "savedAt": "2025-06-04T17:30:32.694Z"
  },
  {
    "id": "6k1Qbba3pn2wHLu7A2m95Q",
    "name": "Wonder 45",
    "genres": [
      "retro soul",
      "indie soul"
    ],
    "followers": 1569,
    "monthlyListeners": 0,
    "image": "https://i.scdn.co/image/ab6761610000e5ebcbf2d01cf62eb36a91d9a788",
    "preview_url": "",
    "source": "spotify",
    "savedAt": "2025-06-04T17:30:32.694Z"
  },
  {
    "id": "2nTjd2lNo1GVEfXM3bCnsh",
    "name": "The Teskey Brothers",
    "genres": [
      "retro soul",
      "soul blues",
      "blues"
    ],
    "followers": 973337,
    "monthlyListeners": 0,
    "image": "https://i.scdn.co/image/ab6761610000e5ebbaf7e1f882e784750e6d7745",
    "preview_url": "",
    "source": "spotify",
    "savedAt": "2025-06-04T17:30:32.694Z"
  },
  {
    "id": "0ZkJ54ZnjZt0ZuoQpXbR8U",
    "name": "Tender Games",
    "genres": [
      "lo-fi house"
    ],
    "followers": 8224,
    "monthlyListeners": 0,
    "image": "https://i.scdn.co/image/ab6761610000e5ebf1d75b0782d4e3826d226ee7",
    "preview_url": "",
    "source": "spotify",
    "savedAt": "2025-06-04T17:30:32.694Z"
  },
  {
    "id": "3E0jeQoIrqwpjGuhSIe7H0",
    "name": "Teddy Grossman",
    "genres": [
      "retro soul",
      "indie soul"
    ],
    "followers": 3264,
    "monthlyListeners": 0,
    "image": "https://i.scdn.co/image/ab6761610000e5ebf3eb5358a630b2f781a1d5a2",
    "preview_url": "",
    "source": "spotify",
    "savedAt": "2025-06-04T17:30:32.694Z"
  },
  {
    "id": "1K0Gi1qUFGSyZUFXvJF4F2",
    "name": "Jon and Roy",
    "genres": [
      "indie folk"
    ],
    "followers": 75359,
    "monthlyListeners": 0,
    "image": "https://i.scdn.co/image/ab6761610000e5eb4c22bca39d01e84d07eb767c",
    "preview_url": "",
    "source": "spotify",
    "savedAt": "2025-06-04T17:30:32.694Z"
  },
  {
    "id": "0XHM5ZNJDU8e4CfbWMeSzC",
    "name": "Roo Panes",
    "genres": [
      "indie folk"
    ],
    "followers": 226449,
    "monthlyListeners": 0,
    "image": "https://i.scdn.co/image/ab6761610000e5ebea89577c4bd75e37c9c31fbb",
    "preview_url": "",
    "source": "spotify",
    "savedAt": "2025-06-04T17:30:32.694Z"
  },
  {
    "id": "6bo2HtqA2nv4hdO20GZsei",
    "name": "Theo Lawrence and The Hearts",
    "genres": [],
    "followers": 2738,
    "monthlyListeners": 0,
    "image": "https://i.scdn.co/image/ab67616d0000b2730c2946479a013c14eaed9ac3",
    "preview_url": "",
    "source": "spotify",
    "savedAt": "2025-06-04T17:30:32.694Z"
  },
  {
    "id": "08yjRkGm8KNsShKjtbEmt6",
    "name": "Hajaj",
    "genres": [
      "retro soul"
    ],
    "followers": 58173,
    "monthlyListeners": 0,
    "image": "https://i.scdn.co/image/ab6761610000e5eb9ecb7fa9a074666dc5b70083",
    "preview_url": "",
    "source": "spotify",
    "savedAt": "2025-06-04T17:30:32.694Z"
  },
  {
    "id": "08xR1XU2SWgC2K0yx6lEYm",
    "name": "Fran Vasilić",
    "genres": [],
    "followers": 120399,
    "monthlyListeners": 0,
    "image": "https://i.scdn.co/image/ab6761610000e5ebadd68a056419e45dc8780b15",
    "preview_url": "",
    "source": "spotify",
    "savedAt": "2025-06-04T17:30:32.694Z"
  },
  {
    "id": "1Mxqyy3pSjf8kZZL4QVxS0",
    "name": "Frank Sinatra",
    "genres": [
      "christmas",
      "big band",
      "adult standards",
      "swing music",
      "vocal jazz",
      "jazz"
    ],
    "followers": 8091626,
    "monthlyListeners": 0,
    "image": "https://i.scdn.co/image/fc4e0f474fb4c4cb83617aa884dc9fd9822d4411",
    "preview_url": "",
    "source": "spotify",
    "savedAt": "2025-06-04T17:30:32.694Z"
  },
  {
    "id": "3Bl4eNAFJkXXi0ewcjgGP9",
    "name": "Seth Walker",
    "genres": [
      "blues",
      "modern blues"
    ],
    "followers": 10376,
    "monthlyListeners": 0,
    "image": "https://i.scdn.co/image/ab6761610000e5eba2c4bd04109b87a71f592f67",
    "preview_url": "",
    "source": "spotify",
    "savedAt": "2025-06-04T17:30:32.694Z"
  },
  {
    "id": "1T2WeXEi0XlZiPpjjDAY0L",
    "name": "Her",
    "genres": [
      "french indie pop"
    ],
    "followers": 175295,
    "monthlyListeners": 0,
    "image": "https://i.scdn.co/image/ab6761610000e5ebf8f15699d75caa8430774789",
    "preview_url": "",
    "source": "spotify",
    "savedAt": "2025-06-04T17:30:32.694Z"
  },
  {
    "id": "7ylX0wSHMxslYD0Tr3SXNG",
    "name": "Denise King",
    "genres": [
      "vocal jazz",
      "bossa nova",
      "smooth jazz"
    ],
    "followers": 14932,
    "monthlyListeners": 0,
    "image": "https://i.scdn.co/image/ab6761610000e5eb4ed32103c73eca0dd7ee1cd1",
    "preview_url": "",
    "source": "spotify",
    "savedAt": "2025-06-04T17:30:32.694Z"
  },
  {
    "id": "1HV8WZw4RiZ1QFiqJpspS0",
    "name": "Toni Green",
    "genres": [
      "soul blues",
      "retro soul"
    ],
    "followers": 2287,
    "monthlyListeners": 0,
    "image": "https://i.scdn.co/image/ab6761610000e5eb1048405e74bd295fa0db0eda",
    "preview_url": "",
    "source": "spotify",
    "savedAt": "2025-06-04T17:30:32.694Z"
  },
  {
    "id": "24WPEGLYPvEsmk4GSDFyST",
    "name": "Jordan Mackampa",
    "genres": [],
    "followers": 105856,
    "monthlyListeners": 0,
    "image": "https://i.scdn.co/image/ab6761610000e5ebc6931208abf6220fcdfe1a45",
    "preview_url": "",
    "source": "spotify",
    "savedAt": "2025-06-04T17:30:32.694Z"
  },
  {
    "id": "5QXLMdpKeByOo5ypH9gT13",
    "name": "Fantastic Negrito",
    "genres": [
      "southern gothic",
      "modern blues",
      "blues rock",
      "blues"
    ],
    "followers": 201053,
    "monthlyListeners": 0,
    "image": "https://i.scdn.co/image/ab6761610000e5ebdcf63ed97e0cff57db3550a4",
    "preview_url": "",
    "source": "spotify",
    "savedAt": "2025-06-04T17:30:32.694Z"
  },
  {
    "id": "7lS8dsCoC7M6QbNp3MRpmw",
    "name": "Jesper Munk",
    "genres": [
      "german indie"
    ],
    "followers": 41476,
    "monthlyListeners": 0,
    "image": "https://i.scdn.co/image/ab6761610000e5eba5811b83da78474f8a297e71",
    "preview_url": "",
    "source": "spotify",
    "savedAt": "2025-06-04T17:30:32.694Z"
  },
  {
    "id": "2dJTa3mUidZAO9sKcY72tK",
    "name": "Ben L'Oncle Soul",
    "genres": [
      "jazz blues",
      "indie soul"
    ],
    "followers": 303025,
    "monthlyListeners": 0,
    "image": "https://i.scdn.co/image/ab6761610000e5eb19216d88b665a54069ecf690",
    "preview_url": "",
    "source": "spotify",
    "savedAt": "2025-06-04T17:30:32.694Z"
  },
  {
    "id": "3U5oimD8ITVHMJQoxypQPN",
    "name": "Nostalgia 77",
    "genres": [
      "nu jazz",
      "jazz blues",
      "acid jazz"
    ],
    "followers": 45467,
    "monthlyListeners": 0,
    "image": "https://i.scdn.co/image/ab6761610000e5eb7e6abedd06b94cf1b754767a",
    "preview_url": "",
    "source": "spotify",
    "savedAt": "2025-06-04T17:30:32.694Z"
  },
  {
    "id": "43l4GGl1QwpqP7R2k43M9W",
    "name": "GeeJay",
    "genres": [],
    "followers": 25746,
    "monthlyListeners": 0,
    "image": "https://i.scdn.co/image/ab6761610000e5eb06c146c3ea6ba7dfcebd7c7d",
    "preview_url": "",
    "source": "spotify",
    "savedAt": "2025-06-04T17:30:32.694Z"
  },
  {
    "id": "1n5S81eeVtaFs2vvo7p234",
    "name": "Joey Landreth",
    "genres": [
      "modern blues"
    ],
    "followers": 21363,
    "monthlyListeners": 0,
    "image": "https://i.scdn.co/image/ab6761610000e5eb49c20e486c5a16bd5ef43607",
    "preview_url": "",
    "source": "spotify",
    "savedAt": "2025-06-04T17:30:32.694Z"
  },
  {
    "id": "7upKfBWNUqe6pSUDxNQa2v",
    "name": "Jan Verstraeten",
    "genres": [],
    "followers": 6917,
    "monthlyListeners": 0,
    "image": "https://i.scdn.co/image/ab6761610000e5eb3f945c7aabc98b041eaa9f88",
    "preview_url": "",
    "source": "spotify",
    "savedAt": "2025-06-04T17:30:32.694Z"
  },
  {
    "id": "2RP4pPHTXlQpDnO9LvR7Yt",
    "name": "Lianne La Havas",
    "genres": [
      "alternative r&b",
      "soul",
      "pop soul"
    ],
    "followers": 975110,
    "monthlyListeners": 0,
    "image": "https://i.scdn.co/image/ab6761610000e5ebf293a7dca5000a26ec0cf16c",
    "preview_url": "",
    "source": "spotify",
    "savedAt": "2025-06-04T17:30:32.694Z"
  },
  {
    "id": "3ODYbknLzVe3cWQzVfbzGB",
    "name": "Tab Benoit",
    "genres": [
      "blues",
      "cajun",
      "modern blues",
      "zydeco",
      "blues rock",
      "country blues"
    ],
    "followers": 98064,
    "monthlyListeners": 0,
    "image": "https://i.scdn.co/image/ab6761610000e5eb2e4eb8ffe11887c4fb355069",
    "preview_url": "",
    "source": "spotify",
    "savedAt": "2025-06-04T17:30:32.694Z"
  },
  {
    "id": "0x7rqFHFpWOBpYVJ1URgSC",
    "name": "Parson Jones",
    "genres": [],
    "followers": 2399,
    "monthlyListeners": 0,
    "image": "https://i.scdn.co/image/ab6761610000e5ebde7783412afef7a7a899b410",
    "preview_url": "",
    "source": "spotify",
    "savedAt": "2025-06-04T17:30:32.694Z"
  },
  {
    "id": "3KikThZktmDtUICg0EOKoJ",
    "name": "Gael Faure",
    "genres": [
      "french pop"
    ],
    "followers": 12042,
    "monthlyListeners": 0,
    "image": "https://i.scdn.co/image/ab6761610000e5eb451e2792b2cd499b1b565220",
    "preview_url": "",
    "source": "spotify",
    "savedAt": "2025-06-04T17:30:32.694Z"
  },
  {
    "id": "1pqbZX6kOvaCi5IEd9zFkG",
    "name": "Rhonda",
    "genres": [
      "retro soul"
    ],
    "followers": 5617,
    "monthlyListeners": 0,
    "image": "https://i.scdn.co/image/ab6761610000e5eb000def5f8ec1069a97b5f976",
    "preview_url": "",
    "source": "spotify",
    "savedAt": "2025-06-04T17:30:32.694Z"
  },
  {
    "id": "43baNkimEScblxgIPkyroW",
    "name": "Josephien",
    "genres": [],
    "followers": 962,
    "monthlyListeners": 0,
    "image": "https://i.scdn.co/image/ab6761610000e5eb52cfbfb4222f1858f5e47c5c",
    "preview_url": "",
    "source": "spotify",
    "savedAt": "2025-06-04T17:30:32.694Z"
  },
  {
    "id": "2c04R4WjyZyi1qiRLPhpsO",
    "name": "otta",
    "genres": [
      "uk r&b",
      "pop soul"
    ],
    "followers": 3659,
    "monthlyListeners": 0,
    "image": "https://i.scdn.co/image/ab6761610000e5eb7df4a72c7bb8d13436f6fba2",
    "preview_url": "",
    "source": "spotify",
    "savedAt": "2025-06-04T17:30:32.694Z"
  },
  {
    "id": "2Mu5NfyYm8n5iTomuKAEHl",
    "name": "Ms. Lauryn Hill",
    "genres": [
      "neo soul"
    ],
    "followers": 3339163,
    "monthlyListeners": 0,
    "image": "https://i.scdn.co/image/ccb108f19352e88d6e69b1093d75a2be5efa1c99",
    "preview_url": "",
    "source": "spotify",
    "savedAt": "2025-06-04T17:30:32.694Z"
  },
  {
    "id": "3nuc29fYGlQbIrwh4yrNWd",
    "name": "Lake Street Dive",
    "genres": [],
    "followers": 679327,
    "monthlyListeners": 0,
    "image": "https://i.scdn.co/image/ab6761610000e5eb65db78e2146a5a48a90c6557",
    "preview_url": "",
    "source": "spotify",
    "savedAt": "2025-06-04T17:30:32.694Z"
  },
  {
    "id": "0FeWKiZSwBRdGzqeCdlH1a",
    "name": "Marcus King",
    "genres": [
      "modern blues",
      "blues rock"
    ],
    "followers": 327079,
    "monthlyListeners": 0,
    "image": "https://i.scdn.co/image/ab6761610000e5eba5b9a2bd65b1ece053eb5911",
    "preview_url": "",
    "source": "spotify",
    "savedAt": "2025-06-04T17:30:32.694Z"
  },
  {
    "id": "5rZUNweztKBI1Xy3XhYHoJ",
    "name": "Danielle Ponder",
    "genres": [
      "retro soul"
    ],
    "followers": 69112,
    "monthlyListeners": 0,
    "image": "https://i.scdn.co/image/ab6761610000e5eb538c1a1030bfbf3b69124253",
    "preview_url": "",
    "source": "spotify",
    "savedAt": "2025-06-04T17:30:32.694Z"
  },
  {
    "id": "41HOzTOe9JNerhym1HWxti",
    "name": "Yann Muller",
    "genres": [
      "lounge",
      "tropical house"
    ],
    "followers": 66402,
    "monthlyListeners": 0,
    "image": "https://i.scdn.co/image/ab6761610000e5eb3bfcf95954e91f4a8c0848dd",
    "preview_url": "",
    "source": "spotify",
    "savedAt": "2025-06-04T17:30:32.694Z"
  },
  {
    "id": "0L7Y276gBjB2pxuyhpgzgv",
    "name": "Kelley Hunt",
    "genres": [
      "blues",
      "zydeco",
      "modern blues",
      "cha cha cha",
      "soul blues",
      "boogie-woogie"
    ],
    "followers": 4218,
    "monthlyListeners": 0,
    "image": "https://i.scdn.co/image/ab6761610000e5ebc6b037ef3570acae8196683c",
    "preview_url": "",
    "source": "spotify",
    "savedAt": "2025-06-04T17:30:32.694Z"
  },
  {
    "id": "7hHpfWb3pePsoynfGjb3wS",
    "name": "Anaut",
    "genres": [
      "retro soul"
    ],
    "followers": 6730,
    "monthlyListeners": 0,
    "image": "https://i.scdn.co/image/ab6761610000e5eb5f7bd74f7264f32874ed16d9",
    "preview_url": "",
    "source": "spotify",
    "savedAt": "2025-06-04T17:30:32.694Z"
  },
  {
    "id": "4qwGe91Bz9K2T8jXTZ815W",
    "name": "Janet Jackson",
    "genres": [
      "new jack swing"
    ],
    "followers": 4059123,
    "monthlyListeners": 0,
    "image": "https://i.scdn.co/image/ab6761610000e5eb24eb85119eb02ae07972fb4b",
    "preview_url": "",
    "source": "spotify",
    "savedAt": "2025-06-04T17:30:32.694Z"
  },
  {
    "id": "43cM1JWUzdfkZCi7rjkPnz",
    "name": "Próxima Parada",
    "genres": [],
    "followers": 77621,
    "monthlyListeners": 0,
    "image": "https://i.scdn.co/image/ab6761610000e5eb829f51343c757c9316aac997",
    "preview_url": "",
    "source": "spotify",
    "savedAt": "2025-06-04T17:30:32.694Z"
  },
  {
    "id": "2r5nTmvuWViPvZaLDRZ1J0",
    "name": "Malted Milk",
    "genres": [
      "retro soul",
      "soul blues",
      "pop soul"
    ],
    "followers": 16566,
    "monthlyListeners": 0,
    "image": "https://i.scdn.co/image/ab6761610000e5eb7fdf9a30f4ecc53cef449260",
    "preview_url": "",
    "source": "spotify",
    "savedAt": "2025-06-04T17:30:32.694Z"
  },
  {
    "id": "4BGagHmgh8YwhvCuUQinnd",
    "name": "Josh Teskey",
    "genres": [
      "blues",
      "modern blues"
    ],
    "followers": 17974,
    "monthlyListeners": 0,
    "image": "https://i.scdn.co/image/ab6761610000e5ebac8fd81265e895b6c93c1dd8",
    "preview_url": "",
    "source": "spotify",
    "savedAt": "2025-06-04T17:30:32.694Z"
  },
  {
    "id": "2tHFi6J76BSMMB6VyWIOeS",
    "name": "Sebastian Schub",
    "genres": [],
    "followers": 59183,
    "monthlyListeners": 0,
    "image": "https://i.scdn.co/image/ab6761610000e5ebea3486f627f15a64af5c0a7b",
    "preview_url": "",
    "source": "spotify",
    "savedAt": "2025-06-04T17:30:32.694Z"
  },
  {
    "id": "2JXmEUolvdLFZc1PoLGC71",
    "name": "Mychelle",
    "genres": [
      "uk r&b",
      "neo soul"
    ],
    "followers": 10226,
    "monthlyListeners": 0,
    "image": "https://i.scdn.co/image/ab6761610000e5ebce0024bc25c4b6695cd10023",
    "preview_url": "",
    "source": "spotify",
    "savedAt": "2025-06-04T17:30:32.694Z"
  },
  {
    "id": "1e16kiJQtCTveTl7TQnkFN",
    "name": "Scary Pockets",
    "genres": [
      "retro soul"
    ],
    "followers": 370934,
    "monthlyListeners": 0,
    "image": "https://i.scdn.co/image/ab6761610000e5ebd3768b9a36bf6d375d6919d7",
    "preview_url": "",
    "source": "spotify",
    "savedAt": "2025-06-04T17:30:32.694Z"
  },
  {
    "id": "4aT85lix0NSNB6w9Ozzksq",
    "name": "OSKA",
    "genres": [],
    "followers": 25586,
    "monthlyListeners": 0,
    "image": "https://i.scdn.co/image/ab6761610000e5ebd81a09dffd19bbfccb579a3f",
    "preview_url": "",
    "source": "spotify",
    "savedAt": "2025-06-04T17:30:32.694Z"
  },
  {
    "id": "3YqIkVQBn7ZXUYdtAMHYhE",
    "name": "Uncle Maximilien",
    "genres": [],
    "followers": 4920,
    "monthlyListeners": 0,
    "image": "https://i.scdn.co/image/ab6761610000e5eba7f35915b72d588b91de0660",
    "preview_url": "",
    "source": "spotify",
    "savedAt": "2025-06-04T17:30:32.694Z"
  },
  {
    "id": "0AepkoQhYvkjEzzwIcGxdV",
    "name": "Jacob Banks",
    "genres": [],
    "followers": 568672,
    "monthlyListeners": 0,
    "image": "https://i.scdn.co/image/ab6761610000e5eb0224cea207d08f81ce1e8294",
    "preview_url": "",
    "source": "spotify",
    "savedAt": "2025-06-04T17:30:32.694Z"
  },
  {
    "id": "10tvYvaoSO32hlvu3NrrPC",
    "name": "Dominique Fils-Aimé",
    "genres": [],
    "followers": 55981,
    "monthlyListeners": 0,
    "image": "https://i.scdn.co/image/ab6761610000e5ebbfda237596cabf04bda2d6a5",
    "preview_url": "",
    "source": "spotify",
    "savedAt": "2025-06-04T17:30:32.694Z"
  },
  {
    "id": "4c4aEmXU6Hx95REbIZ3S82",
    "name": "Rozzi",
    "genres": [],
    "followers": 48933,
    "monthlyListeners": 0,
    "image": "https://i.scdn.co/image/ab6761610000e5ebb957ff792c1f9e3e7197c399",
    "preview_url": "",
    "source": "spotify",
    "savedAt": "2025-06-04T17:30:32.694Z"
  },
  {
    "id": "6O0WkZMlHi7yqizwsA8uVf",
    "name": "The Meltdown",
    "genres": [
      "retro soul",
      "soul blues"
    ],
    "followers": 51399,
    "monthlyListeners": 0,
    "image": "https://i.scdn.co/image/ab6761610000e5eb6bc7c9a3d00a8689ed22fe23",
    "preview_url": "",
    "source": "spotify",
    "savedAt": "2025-06-04T17:30:32.694Z"
  },
  {
    "id": "5lcDGoJUr5WY5bCFAfYbCU",
    "name": "KIRBY",
    "genres": [
      "alternative r&b"
    ],
    "followers": 280390,
    "monthlyListeners": 0,
    "image": "https://i.scdn.co/image/ab6761610000e5eb691399c2907148330a1d2afb",
    "preview_url": "",
    "source": "spotify",
    "savedAt": "2025-06-04T17:30:32.694Z"
  },
  {
    "id": "1ycLm9xOZGiFjSTwYnIjWa",
    "name": "Nino Pinelli",
    "genres": [],
    "followers": 1853,
    "monthlyListeners": 0,
    "image": "https://i.scdn.co/image/ab67616d0000b2736860984eeb89d05ac5b2dbb2",
    "preview_url": "",
    "source": "spotify",
    "savedAt": "2025-06-04T17:30:32.694Z"
  },
  {
    "id": "0WwSkZ7LtFUFjGjMZBMt6T",
    "name": "Dire Straits",
    "genres": [
      "classic rock"
    ],
    "followers": 8488105,
    "monthlyListeners": 0,
    "image": "https://i.scdn.co/image/ab6761610000e5eb4bdaa8c5e65b64f50549c393",
    "preview_url": "",
    "source": "spotify",
    "savedAt": "2025-06-04T17:30:32.694Z"
  },
  {
    "id": "1JfNRa6vkoWP0k2UASfk7e",
    "name": "Caitlin",
    "genres": [],
    "followers": 3120,
    "monthlyListeners": 0,
    "image": "https://i.scdn.co/image/ab6761610000e5ebda7dcfa0dc751f3dba3b3e22",
    "preview_url": "",
    "source": "spotify",
    "savedAt": "2025-06-04T17:30:32.694Z"
  },
  {
    "id": "04ka9403wgTxmWFMY1PD5t",
    "name": "Judith Hill",
    "genres": [
      "retro soul",
      "neo soul"
    ],
    "followers": 65270,
    "monthlyListeners": 0,
    "image": "https://i.scdn.co/image/ab6761610000e5eb2d8d2473cce0976489bd0260",
    "preview_url": "",
    "source": "spotify",
    "savedAt": "2025-06-04T17:30:32.694Z"
  },
  {
    "id": "0ScLk4lNexNrtkDmGQicRx",
    "name": "Jesse Gold",
    "genres": [],
    "followers": 55113,
    "monthlyListeners": 0,
    "image": "https://i.scdn.co/image/ab6761610000e5eb430870ae72640dfeebdfd821",
    "preview_url": "",
    "source": "spotify",
    "savedAt": "2025-06-04T17:30:32.694Z"
  },
  {
    "id": "4lujUKeO6nQAJXpq37Epn7",
    "name": "Son Little",
    "genres": [
      "retro soul",
      "soul"
    ],
    "followers": 175045,
    "monthlyListeners": 0,
    "image": "https://i.scdn.co/image/ab6761610000e5eb7321188756fe1f5d4b554797",
    "preview_url": "",
    "source": "spotify",
    "savedAt": "2025-06-04T17:30:32.694Z"
  },
  {
    "id": "0VEzhZrWBCaoufAiZkjX3G",
    "name": "Marbert Rocel",
    "genres": [],
    "followers": 42647,
    "monthlyListeners": 0,
    "image": "https://i.scdn.co/image/ab6761610000e5eb263673022352513435da64ba",
    "preview_url": "",
    "source": "spotify",
    "savedAt": "2025-06-04T17:30:32.694Z"
  },
  {
    "id": "2xlu6WzVa7WHwHhRptqq7c",
    "name": "Ida Sand",
    "genres": [
      "vocal jazz"
    ],
    "followers": 23091,
    "monthlyListeners": 0,
    "image": "https://i.scdn.co/image/ab6761610000e5eb2a0b039300c6dddde1f09beb",
    "preview_url": "",
    "source": "spotify",
    "savedAt": "2025-06-04T17:30:32.694Z"
  },
  {
    "id": "04HjibunL2jGRLEqVEMfZY",
    "name": "Ash Grunwald",
    "genres": [
      "blues",
      "modern blues",
      "blues rock"
    ],
    "followers": 48596,
    "monthlyListeners": 0,
    "image": "https://i.scdn.co/image/ab6761610000e5ebd73a27613cb752c2f706b859",
    "preview_url": "",
    "source": "spotify",
    "savedAt": "2025-06-04T17:30:32.694Z"
  },
  {
    "id": "3JVVGMRtCA1lsynAOn8AU6",
    "name": "Ivan Hartle",
    "genres": [
      "retro soul",
      "indie soul"
    ],
    "followers": 4203,
    "monthlyListeners": 0,
    "image": "https://i.scdn.co/image/ab6761610000e5ebbcac3c8dcaf36d0765147a7d",
    "preview_url": "",
    "source": "spotify",
    "savedAt": "2025-06-04T17:30:32.694Z"
  },
  {
    "id": "2t9yJDJIEtvPmr2iRIdqBf",
    "name": "Fink",
    "genres": [
      "indie folk"
    ],
    "followers": 380433,
    "monthlyListeners": 0,
    "image": "https://i.scdn.co/image/ab6761610000e5eb6781f54cfdb4267a91272daf",
    "preview_url": "",
    "source": "spotify",
    "savedAt": "2025-06-04T17:30:32.694Z"
  },
  {
    "id": "0Vd8YQz8TYk2vSKEYVvIgL",
    "name": "Dojo Cuts",
    "genres": [
      "retro soul"
    ],
    "followers": 81553,
    "monthlyListeners": 0,
    "image": "https://i.scdn.co/image/ab6761610000e5eb75ebbd8f35c61280d6c6dbee",
    "preview_url": "",
    "source": "spotify",
    "savedAt": "2025-06-04T17:30:32.694Z"
  },
  {
    "id": "23usQJ95w7f95tnN4MJEgy",
    "name": "Jono McCleery",
    "genres": [
      "liquid funk"
    ],
    "followers": 30500,
    "monthlyListeners": 0,
    "image": "https://i.scdn.co/image/ab6761610000e5eb5c61f71e27d3ec4493d20d0f",
    "preview_url": "",
    "source": "spotify",
    "savedAt": "2025-06-04T17:30:32.694Z"
  },
  {
    "id": "1HY2Jd0NmPuamShAr6KMms",
    "name": "Lady Gaga",
    "genres": [
      "art pop",
      "pop"
    ],
    "followers": 38548406,
    "monthlyListeners": 0,
    "image": "https://i.scdn.co/image/ab6761610000e5ebaadc18cac8d48124357c38e6",
    "preview_url": "",
    "source": "spotify",
    "savedAt": "2025-06-04T17:30:32.694Z"
  },
  {
    "id": "0fTSzq9jAh4c36UVb4V7CB",
    "name": "Alex Warren",
    "genres": [],
    "followers": 1568465,
    "monthlyListeners": 0,
    "image": "https://i.scdn.co/image/ab6761610000e5ebe5547931c7f652c2ece8b76c",
    "preview_url": "",
    "source": "spotify",
    "savedAt": "2025-06-04T17:30:32.694Z"
  },
  {
    "id": "3eVa5w3URK5duf6eyVDbu9",
    "name": "ROSÉ",
    "genres": [
      "k-pop"
    ],
    "followers": 11647284,
    "monthlyListeners": 0,
    "image": "https://i.scdn.co/image/ab6761610000e5ebcfb4350222919670128ff2dc",
    "preview_url": "",
    "source": "spotify",
    "savedAt": "2025-06-04T17:30:32.694Z"
  },
  {
    "id": "74KM79TiuVKeVCqs8QtB0B",
    "name": "Sabrina Carpenter",
    "genres": [],
    "followers": 23028962,
    "monthlyListeners": 0,
    "image": "https://i.scdn.co/image/ab6761610000e5eb0f06b6f6d9d36ea167be248d",
    "preview_url": "",
    "source": "spotify",
    "savedAt": "2025-06-04T17:30:32.694Z"
  },
  {
    "id": "66CXWjxzNUsdJxJ2JdwvnR",
    "name": "Ariana Grande",
    "genres": [
      "pop"
    ],
    "followers": 105558480,
    "monthlyListeners": 0,
    "image": "https://i.scdn.co/image/ab6761610000e5eb6725802588d7dc1aba076ca5",
    "preview_url": "",
    "source": "spotify",
    "savedAt": "2025-06-04T17:30:32.694Z"
  },
  {
    "id": "1iCnM8foFssWlPRLfAbIwo",
    "name": "Gigi Perez",
    "genres": [],
    "followers": 1246403,
    "monthlyListeners": 0,
    "image": "https://i.scdn.co/image/ab6761610000e5ebd58f13475be93b37bb63893f",
    "preview_url": "",
    "source": "spotify",
    "savedAt": "2025-06-04T17:30:32.694Z"
  },
  {
    "id": "06HL4z0CvFAxyc27GXpf02",
    "name": "Taylor Swift",
    "genres": [],
    "followers": 138385381,
    "monthlyListeners": 0,
    "image": "https://i.scdn.co/image/ab6761610000e5ebe672b5f553298dcdccb0e676",
    "preview_url": "",
    "source": "spotify",
    "savedAt": "2025-06-04T17:30:32.694Z"
  },
  {
    "id": "6qqNVTkY8uBg9cP3Jd7DAH",
    "name": "Billie Eilish",
    "genres": [],
    "followers": 112674740,
    "monthlyListeners": 0,
    "image": "https://i.scdn.co/image/ab6761610000e5eb4a21b4760d2ecb7b0dcdc8da",
    "preview_url": "",
    "source": "spotify",
    "savedAt": "2025-06-04T17:30:32.694Z"
  },
  {
    "id": "5YGY8feqx7naU7z4HrwZM6",
    "name": "Miley Cyrus",
    "genres": [],
    "followers": 26040285,
    "monthlyListeners": 0,
    "image": "https://i.scdn.co/image/ab6761610000e5ebf4cccd14ec026038d713e353",
    "preview_url": "",
    "source": "spotify",
    "savedAt": "2025-06-04T17:30:32.694Z"
  },
  {
    "id": "2wY79sveU1sp5g7SokKOiI",
    "name": "Sam Smith",
    "genres": [
      "soft pop"
    ],
    "followers": 25844464,
    "monthlyListeners": 0,
    "image": "https://i.scdn.co/image/ab6761610000e5ebc4c97d96c08e4bb7c5f574aa",
    "preview_url": "",
    "source": "spotify",
    "savedAt": "2025-06-04T17:30:32.694Z"
  },
  {
    "id": "5Pwc4xIPtQLFEnJriah9YJ",
    "name": "OneRepublic",
    "genres": [
      "soft pop"
    ],
    "followers": 18319750,
    "monthlyListeners": 0,
    "image": "https://i.scdn.co/image/ab6761610000e5eb57138b98e7ddd5a86ee97a9b",
    "preview_url": "",
    "source": "spotify",
    "savedAt": "2025-06-04T17:30:32.694Z"
  }
]